ps2mc_browser/__init__.py
ps2mc_browser/browser.py
ps2mc_browser/error.py
ps2mc_browser/icon.py
ps2mc_browser/models.py
ps2mc_browser/ps2mc.py
ps2mc_browser/utils.py
ps2mc_browser/wxcanvas.py
ps2mc_browser/wxwindow.py
ps2mc_browser/shaders/__init__.py
ps2mc_browser/shaders/bg.frag
ps2mc_browser/shaders/bg.vert
ps2mc_browser/shaders/circle.frag
ps2mc_browser/shaders/circle.vert
ps2mc_browser/shaders/icon.frag
ps2mc_browser/shaders/icon.vert
ps2mc_browser-1.0.0.dist-info/METADATA
ps2mc_browser-1.0.0.dist-info/WHEEL
ps2mc_browser-1.0.0.dist-info/entry_points.txt
ps2mc_browser-1.0.0.dist-info/licenses/LICENSE
ps2mc_browser-1.0.0.dist-info/RECORD
