Metadata-Version: 2.4
Name: ps2mc-browser
Version: 1.0.0
Summary: A PS2 save file viewer with OpenGL 3D icon rendering support.
Project-URL: Homepage, https://github.com/caol64/ps2mc-browser
Author-email: Lei <caol64@gmail.com>
License-Expression: MIT
License-File: LICENSE
Classifier: Development Status :: 5 - Production/Stable
Classifier: Environment :: MacOS X :: Cocoa
Classifier: Environment :: Win32 (MS Windows)
Classifier: Environment :: X11 Applications :: GTK
Classifier: Intended Audience :: End Users/Desktop
Classifier: License :: OSI Approved :: MIT License
Classifier: Operating System :: OS Independent
Classifier: Programming Language :: Python :: 3.10
Classifier: Programming Language :: Python :: 3.11
Classifier: Programming Language :: Python :: 3.12
Classifier: Programming Language :: Python :: 3.13
Classifier: Topic :: Multimedia :: Graphics
Classifier: Topic :: Software Development :: User Interfaces
Classifier: Topic :: Utilities
Requires-Python: >=3.10
Requires-Dist: moderngl==5.8.2
Requires-Dist: numpy==1.26.4
Requires-Dist: pyglm==2.7.1
Requires-Dist: wxpython==4.2.1
Provides-Extra: dev
Requires-Dist: build==1.2.2; extra == 'dev'
Requires-Dist: pyinstaller==6.11.1; extra == 'dev'
Requires-Dist: tomli==2.2.1; extra == 'dev'
